AUTHORS.rst
CHANGELOG.rst
LICENSE
MANIFEST.in
README.rst
requirements.txt
setup.cfg
setup.py
tox.ini
src/.DS_Store
src/digs/.DS_Store
src/digs/__init__.py
src/digs/__main__.py
src/digs/logger.py
src/digs/use.py
src/digs/utils.py
src/digs/worker.py
src/digs.egg-info/PKG-INFO
src/digs.egg-info/SOURCES.txt
src/digs.egg-info/dependency_links.txt
src/digs.egg-info/entry_points.txt
src/digs.egg-info/not-zip-safe
src/digs.egg-info/requires.txt
src/digs.egg-info/top_level.txt
src/digs/gui/__init__.py
src/digs/gui/__main__.py
src/digs/gui/constants.py
src/digs/gui/start.py
src/digs/gui/window.py