Metadata-Version: 1.1
Name: digs
Version: 0.1.7
Summary: Making easier the text crawling tasks over websites with depth levels.
Home-page: https://github.com/d555/digs
Author: Jonathan S. Prieto C.
Author-email: prieto.jona@gmail.com
License: BSD
Keywords: crawling,crawler,web,text,extraction,scraper,scrapy,scraping,links,html2txt,atxt,linkgrabber,beautifulsoup,html,parser,hyperlinks
Platform: UNKNOWN
Classifier: Development Status :: 4 - Beta
Classifier: Development Status :: 2 - Pre-Alpha
Classifier: Environment :: Console
Classifier: Programming Language :: Python
Classifier: Programming Language :: Python :: 2.7
Classifier: Programming Language :: Python :: 3
Classifier: Programming Language :: Python :: 3.3
Classifier: Topic :: Utilities
Classifier: Topic :: Internet :: WWW/HTTP
